cflashfiles/FlashFiles.py
cflashfiles/__init__.py
cflashfiles/_version.py
cflashfiles/archive.py
cflashfiles/asyn.py
cflashfiles/caching.py
cflashfiles/callbacks.py
cflashfiles/compression.py
cflashfiles/conftest.py
cflashfiles/core.py
cflashfiles/dircache.py
cflashfiles/exceptions.py
cflashfiles/fuse.py
cflashfiles/generic.py
cflashfiles/mapping.py
cflashfiles/parquet.py
cflashfiles/registry.py
cflashfiles/spec.py
cflashfiles/transaction.py
cflashfiles/utils.py
cflashfiles-2.3.dist-info/METADATA
cflashfiles-2.3.dist-info/WHEEL
cflashfiles-2.3.dist-info/top_level.txt
cflashfiles-2.3.dist-info/RECORD
